mcp_subscribe/__init__.py
mcp_subscribe/server.py
mcp_subscribe/util.py
mcp_subscribe-0.1.0.dist-info/METADATA
mcp_subscribe-0.1.0.dist-info/WHEEL
mcp_subscribe-0.1.0.dist-info/entry_points.txt
mcp_subscribe-0.1.0.dist-info/RECORD
