Metadata-Version: 2.3
Name: mcp-subscribe
Version: 0.1.0
Summary: mcp subscribe proxy
Requires-Python: >=3.12
Classifier: Programming Language :: Python :: 3
Classifier: Programming Language :: Python :: 3.12
Classifier: Programming Language :: Python :: 3.13
Requires-Dist: mcp (>=1.6.0)
